offchain/__init__.py
offchain/base/__init__.py
offchain/base/base_model.py
offchain/base/types.py
offchain/concurrency.py
offchain/constants/__init__.py
offchain/constants/addresses.py
offchain/constants/providers.py
offchain/logger/__init__.py
offchain/logger/logging.py
offchain/metadata/__init__.py
offchain/metadata/adapters/__init__.py
offchain/metadata/adapters/arweave.py
offchain/metadata/adapters/base_adapter.py
offchain/metadata/adapters/data_uri.py
offchain/metadata/adapters/default_adapter_configs.py
offchain/metadata/adapters/http_adapter.py
offchain/metadata/adapters/ipfs.py
offchain/metadata/constants/__init__.py
offchain/metadata/constants/autoglyphs.py
offchain/metadata/constants/nouns.py
offchain/metadata/fetchers/__init__.py
offchain/metadata/fetchers/base_fetcher.py
offchain/metadata/fetchers/metadata_fetcher.py
offchain/metadata/get_token_metadata.py
offchain/metadata/models/__init__.py
offchain/metadata/models/metadata.py
offchain/metadata/models/metadata_processing_error.py
offchain/metadata/models/token.py
offchain/metadata/parsers/__init__.py
offchain/metadata/parsers/base_parser.py
offchain/metadata/parsers/catchall/__init__.py
offchain/metadata/parsers/catchall/catchall_parser.py
offchain/metadata/parsers/catchall/default_catchall.py
offchain/metadata/parsers/collection/__init__.py
offchain/metadata/parsers/collection/artblocks.py
offchain/metadata/parsers/collection/autoglyphs.py
offchain/metadata/parsers/collection/chainrunners.py
offchain/metadata/parsers/collection/collection_parser.py
offchain/metadata/parsers/collection/decentraland.py
offchain/metadata/parsers/collection/ens.py
offchain/metadata/parsers/collection/foundation.py
offchain/metadata/parsers/collection/hashmasks.py
offchain/metadata/parsers/collection/loot.py
offchain/metadata/parsers/collection/makersplace.py
offchain/metadata/parsers/collection/nouns.py
offchain/metadata/parsers/collection/punks.py
offchain/metadata/parsers/collection/superrare.py
offchain-0.3.5.dist-info/LICENSE
offchain-0.3.5.dist-info/METADATA
offchain-0.3.5.dist-info/WHEEL
offchain-0.3.5.dist-info/RECORD
