Metadata-Version: 2.1
Name: offchain
Version: 0.3.5
Summary: Open source metadata processing framework
Author: Zora eng
Author-email: eng@zora.co
Requires-Python: >=3.9,<4
Classifier: Programming Language :: Python :: 3
Classifier: Programming Language :: Python :: 3.9
Classifier: Programming Language :: Python :: 3.10
Classifier: Programming Language :: Python :: 3.11
Classifier: Programming Language :: Python :: 3.12
Requires-Dist: aiohttp (>=3.8.5,<4.0.0)
Requires-Dist: httpx (>=0.25.0,<0.26.0)
Requires-Dist: pydantic (>=1.9.2,<2.0.0)
Requires-Dist: python-json-logger (>=2.0.4,<3.0.0)
Requires-Dist: requests (>=2.28.1,<3.0.0)
Requires-Dist: ruff (>=0.0.290,<0.0.291)
Requires-Dist: tenacity (>=8.0.1,<9.0.0)
Requires-Dist: types-requests (>=2.31.0.2,<3.0.0.0)
Requires-Dist: urllib3 (>=1.26.11,<2.0.0)
Requires-Dist: web3 (>=6.11.3,<7.0.0)
Project-URL: Documentation, https://ourzora.github.io/offchain
